envs/__init__.py
mappers/__init__.py
swagern/__init__.py
swagern/main.py
swagern/tavern_utils/__init__.py
swagern/tavern_utils/fuzzy_matching.py
swagern/tavern_utils/template_engine.py
swagern/templates/__init__.py
swagern/templates/tavern_template_default.yaml
swagger/__init__.py
swagern-0.1.dist-info/METADATA
swagern-0.1.dist-info/WHEEL
swagern-0.1.dist-info/entry_points.txt
swagern-0.1.dist-info/top_level.txt
swagern-0.1.dist-info/RECORD
