Metadata-Version: 2.1
Name: swagern
Version: 0.1
Summary: A command-line tool for generating Tavern test cases from Swagger API specifications.
Author: Varsha Ryali, Trilokesh Chandra Barua, Anthony Fernandes, Shubhra Debnath
Author-email: varsha.ryali@newfold.com, trilokesh.barua@newfold.com, anthony.fernandes@newfold.com, shubhra.debnath@newfold.com, 
Requires-Dist: click
Requires-Dist: PyYAML
Requires-Dist: jinja2 ==3.1.2
Requires-Dist: requests ==2.26.0
Requires-Dist: Tavern ==1.0.0
Requires-Dist: fuzzywuzzy ==0.18.0
Requires-Dist: pytest-sugar
